setup.py
seed/__init__.py
seed.tensor.egg-info/PKG-INFO
seed.tensor.egg-info/SOURCES.txt
seed.tensor.egg-info/dependency_links.txt
seed.tensor.egg-info/requires.txt
seed.tensor.egg-info/top_level.txt
seed/tensor/__init__.py
seed/tensor/mc.py