Metadata-Version: 1.1
Name: seed.tensor
Version: 0.0.4
Summary: Tensor sources for Seed components
Home-page: http://github.com/praekeltfoundation/seed-tensor
Author: Colin Alston
Author-email: colin@praekelt.com
License: MIT
Platform: UNKNOWN
Classifier: Development Status :: 4 - Beta
Classifier: Intended Audience :: System Administrators
Classifier: License :: OSI Approved :: MIT License
Classifier: Operating System :: POSIX
Classifier: Programming Language :: Python
Classifier: Topic :: System :: Distributed Computing
